purpleair_api/PurpleAirAPI.py
purpleair_api/PurpleAirAPIConstants.py
purpleair_api/PurpleAirAPIError.py
purpleair_api/PurpleAirAPIHelpers.py
purpleair_api/PurpleAirLocalAPI.py
purpleair_api/PurpleAirReadAPI.py
purpleair_api/PurpleAirWriteAPI.py
purpleair_api/__init__.py
purpleair_api-1.3.0.dist-info/LICENSE
purpleair_api-1.3.0.dist-info/METADATA
purpleair_api-1.3.0.dist-info/WHEEL
purpleair_api-1.3.0.dist-info/top_level.txt
purpleair_api-1.3.0.dist-info/RECORD
