Metadata-Version: 2.2
Name: purpleair_api
Version: 1.3.0
Home-page: https://github.com/carlkidcrypto/purpleair_api
Author: Carlos Santos
Author-email: dose.lucky.sake@cloak.id
License: MIT
Keywords: purpleair_api,purple air api,purple_air,purple air,purpleair_sensor,purpleair sensor,purpleair-sensor
Platform: Windows 32/64
Platform: Linux 32/64
Platform: MacOS 32/64
Requires-Python: <3.14,>=3.9
License-File: LICENSE
Requires-Dist: requests
